acpipe_acjson/__init__.py
acpipe_acjson/acjson.py
acpipe_acjson/error.json
acpipe_acjson/test_acjson.py
acpipe_acjson-0.1.17.dist-info/LICENSE.txt
acpipe_acjson-0.1.17.dist-info/LICENSE.txt~
acpipe_acjson-0.1.17.dist-info/METADATA
acpipe_acjson-0.1.17.dist-info/WHEEL
acpipe_acjson-0.1.17.dist-info/top_level.txt
acpipe_acjson-0.1.17.dist-info/RECORD
