Metadata-Version: 2.1
Name: acpipe-acjson
Version: 0.1.17
Summary: acpipe_acjson is the python3 acjson base library. acjson - assay coordinate json - is a file format developed to log complicated biological wetlab experiment layouts.
Home-page: https://gitlab.com/biotransistor/acpipe_acjson
Author: Elmar Bucher
Author-email: ulmusfagus@zoho.com
License: GPL>=3
Keywords: bioinformatics json wetlab experiment log_fomat
Platform: UNKNOWN
Classifier: Development Status :: 4 - Beta
Classifier: Intended Audience :: Developers
Classifier: Intended Audience :: Science/Research
Classifier: Operating System :: POSIX :: Linux
Classifier: Operating System :: MacOS :: MacOS X
Classifier: Operating System :: Microsoft :: Windows
Classifier: Topic :: Scientific/Engineering :: Bio-Informatics
Classifier: License :: OSI Approved :: GNU General Public License v3 or later (GPLv3+)
Classifier: Programming Language :: Python :: 3
Requires-Python: >=3
